floweaver/__init__.py
floweaver/augment_view_graph.py
floweaver/color_scales.py
floweaver/dataset.py
floweaver/dummy_nodes.py
floweaver/graph_to_sankey.py
floweaver/hierarchy.py
floweaver/layered_graph.py
floweaver/ordering.py
floweaver/partition.py
floweaver/results_graph.py
floweaver/sankey_data.py
floweaver/sankey_definition.py
floweaver/save_sankey.py
floweaver/sentinel.py
floweaver/utils.py
floweaver/view_graph.py
floweaver/weave.py
floweaver-2.0.1.dist-info/LICENSE
floweaver-2.0.1.dist-info/METADATA
floweaver-2.0.1.dist-info/WHEEL
floweaver-2.0.1.dist-info/top_level.txt
floweaver-2.0.1.dist-info/RECORD
