Metadata-Version: 2.1
Name: floweaver
Version: 2.0.1
Summary: View flow data as Sankey diagrams.
Home-page: https://github.com/ricklupton/floweaver
Author: Rick Lupton
Author-email: mail@ricklupton.name
License: UNKNOWN
Keywords: Sankey diagram flow data visualisation
Platform: UNKNOWN
Classifier: Development Status :: 4 - Beta
Classifier: Intended Audience :: Developers
Classifier: License :: OSI Approved :: MIT License
Classifier: Programming Language :: Python :: 3
Classifier: Programming Language :: Python :: 3.5
Classifier: Programming Language :: Python :: 3.6
Classifier: Programming Language :: Python :: 3.7
Requires-Python: >=3.5
Provides-Extra: dev
Provides-Extra: test
Provides-Extra: docs
License-File: LICENSE
